TurboTouchPredictor/OneEuroVectorProcessor.py
TurboTouchPredictor/TTPconfig.py
TurboTouchPredictor/TurboTouchPredictor.py
TurboTouchPredictor/__init__.py
TurboTouchPredictor/pAttribut.py
TurboTouchPredictor-0.1.5.dist-info/LICENSE.md
TurboTouchPredictor-0.1.5.dist-info/METADATA
TurboTouchPredictor-0.1.5.dist-info/WHEEL
TurboTouchPredictor-0.1.5.dist-info/top_level.txt
TurboTouchPredictor-0.1.5.dist-info/RECORD
