Metadata-Version: 2.1
Name: TurboTouchPredictor
Version: 0.1.5
Summary: TurboTouch predictor
Home-page: https://github.com/LokiResearch/TurboTouchPredictor/python
Author: Flavien Volant and Géry Casiez
Author-email: gery.casiez@univ-lille.fr
Classifier: Programming Language :: Python :: 3
Classifier: License :: OSI Approved :: BSD License
License-File: LICENSE.md
Requires-Dist: OneEuroFilter
